setup.py
ginkgo_yan/__init__.py
ginkgo_yan/helloginkgo.py
ginkgo_yan.egg-info/PKG-INFO
ginkgo_yan.egg-info/SOURCES.txt
ginkgo_yan.egg-info/dependency_links.txt
ginkgo_yan.egg-info/top_level.txt