Metadata-Version: 1.0
Name: ginkgo-yan
Version: 1.0.0.0
Summary: The first Pypi
Home-page: https://python.org
Author: Yan yanxiang
Author-email: ginkgou@qq.com
License: UNKNOWN
Platform: UNKNOWN
